{
  "runs": [
  {
    "skill": "rs-spec",
    "startedAt": "2026-04-16T04:11:35Z",
    "completedAt": "2026-04-16T04:16:16Z",
    "durationSeconds": 281,
    "iterations": null,
    "stories": null
  }
,
  {
    "skill": "rs-impl",
    "startedAt": "2026-04-16T04:16:33Z",
    "completedAt": "2026-04-16T04:27:14Z",
    "durationSeconds": 641,
    "iterations": 3,
    "stories": {"US-101":{"attempts":1},"US-102":{"attempts":1},"US-103":{"attempts":1},"US-104":{"attempts":1},"US-105":{"attempts":1},"US-201":{"attempts":2},"US-202":{"attempts":1},"US-203":{"attempts":1},"US-301":{"attempts":1},"US-401":{"attempts":2},"US-501":{"attempts":1},"US-502":{"attempts":1}}
  }
  ]
}
